{"type":"FeatureCollection","features":[{"type":"Feature","properties":{"code":"dunkirk","name":"Port of Dunkirk","featureType":"port","portType":"Bulk Port","country":"France"},"geometry":{"type":"Point","coordinates":[2.37,51.05]}}]}