{"type":"FeatureCollection","features":[{"type":"Feature","properties":{"code":"freetown","name":"Port of Freetown","featureType":"port","portType":"Multi-Purpose Port","country":"Sierra Leone"},"geometry":{"type":"Point","coordinates":[-13.23,8.49]}}]}