{"type":"FeatureCollection","features":[{"type":"Feature","properties":{"code":"libreville","name":"Port of Libreville","featureType":"port","portType":"Oil/Gas Terminal","country":"Gabon"},"geometry":{"type":"Point","coordinates":[9.45,0.39]}}]}