{"type":"FeatureCollection","features":[{"type":"Feature","properties":{"code":"lome","name":"Port of Lomé","featureType":"port","portType":"Container Port","country":"Togo"},"geometry":{"type":"Point","coordinates":[1.29,6.13]}}]}