{"type":"FeatureCollection","features":[{"type":"Feature","properties":{"code":"los-angeles","name":"Port of Los Angeles","featureType":"port","portType":"Container Port","country":"United States"},"geometry":{"type":"Point","coordinates":[-118.27,33.74]}}]}