{"type":"FeatureCollection","features":[{"type":"Feature","properties":{"code":"south-louisiana","name":"Port of South Louisiana","featureType":"port","portType":"Bulk Port","country":"United States"},"geometry":{"type":"Point","coordinates":[-90.67,30.05]}}]}