{"type":"FeatureCollection","features":[{"type":"Feature","properties":{"code":"walvis-bay","name":"Port of Walvis Bay","featureType":"port","portType":"Multi-Purpose Port","country":"Namibia"},"geometry":{"type":"Point","coordinates":[14.51,-22.96]}}]}