{"type":"FeatureCollection","features":[{"type":"Feature","properties":{"code":"mia","name":"Miami International","featureType":"airport","iataCode":"MIA","annualPassengers":52500000,"classification":"Major Hub"},"geometry":{"type":"Point","coordinates":[-80.287,25.7959]}}]}
