{"type":"FeatureCollection","features":[{"type":"Feature","properties":{"code":"barcelona","name":"Port of Barcelona","featureType":"port","portType":"Container Port","country":"Spain"},"geometry":{"type":"Point","coordinates":[2.18,41.37]}}]}