{"type":"FeatureCollection","features":[{"type":"Feature","properties":{"code":"cochin","name":"Port of Cochin","featureType":"port","portType":"Container Port","country":"India"},"geometry":{"type":"Point","coordinates":[76.27,9.97]}}]}