{"type":"FeatureCollection","features":[{"type":"Feature","properties":{"code":"kandla","name":"Port of Kandla","featureType":"port","portType":"Bulk Port","country":"India"},"geometry":{"type":"Point","coordinates":[70.22,23.03]}}]}