{"type":"FeatureCollection","features":[{"type":"Feature","properties":{"code":"novorossiysk","name":"Port of Novorossiysk","featureType":"port","portType":"Oil/Gas Terminal","country":"Russia"},"geometry":{"type":"Point","coordinates":[37.78,44.72]}}]}