{"type":"FeatureCollection","features":[{"type":"Feature","properties":{"code":"penang","name":"Port of Penang","featureType":"port","portType":"Multi-Purpose Port","country":"Malaysia"},"geometry":{"type":"Point","coordinates":[100.35,5.42]}}]}