{"type":"FeatureCollection","features":[{"type":"Feature","properties":{"code":"sydney","name":"Port of Sydney","featureType":"port","portType":"Container Port","country":"Australia"},"geometry":{"type":"Point","coordinates":[151.21,-33.86]}}]}