{"type":"FeatureCollection","features":[{"type":"Feature","geometry":{"type":"Point","coordinates":[-80.6041,28.6082]},"properties":{"code":"lc-39a","name":"Launch Complex 39A (Kennedy Space Center)","status":"Active","country":"United States","operator":"SpaceX"}}]}
