{"type":"FeatureCollection","features":[{"type":"Feature","geometry":{"type":"Point","coordinates":[-75.488,37.834]},"properties":{"code":"mid-atlantic-regional","name":"Mid-Atlantic Regional Spaceport (MARS)","status":"Active","country":"United States","operator":"Virginia Space"}}]}
