{"type":"FeatureCollection","features":[{"type":"Feature","geometry":{"type":"Point","coordinates":[-75.487,37.841]},"properties":{"code":"rocket-lab-lc3","name":"Rocket Lab Launch Complex 3","status":"Planned","country":"United States","operator":"Rocket Lab"}}]}
