{"type":"FeatureCollection","features":[{"type":"Feature","geometry":{"type":"Point","coordinates":[130.969,30.401]},"properties":{"code":"tanegashima","name":"Tanegashima Space Center","status":"Active","country":"Japan","operator":"JAXA"}}]}
