{"type":"FeatureCollection","features":[{"type":"Feature","geometry":{"type":"Point","coordinates":[140.0089,40.2281]},"properties":{"code":"uchinada","name":"Noshiro Rocket Testing Center","status":"Active","country":"Japan","operator":"JAXA"}}]}
