{"type":"FeatureCollection","features":[{"type":"Feature","geometry":{"type":"Point","coordinates":[-120.5724,34.742]},"properties":{"code":"vandenberg-sfb","name":"Vandenberg Space Force Base","status":"Active","country":"United States","operator":"USSF / SpaceX / ULA"}}]}
