{"type":"FeatureCollection","features":[{"type":"Feature","geometry":{"type":"Point","coordinates":[110.951,19.6145]},"properties":{"code":"wenchang","name":"Wenchang Space Launch Site","status":"Active","country":"China","operator":"CNSA / CASC"}}]}
