{
  "type": "FeatureCollection",
  "features": [
    {
      "type": "Feature",
      "geometry": {
        "type": "Point",
        "coordinates": [
          16.72272222,
          47.71927778
        ]
      },
      "properties": {
        "code": "ferto-neusiedlersee-cultural-landscape",
        "name": "Fertö / Neusiedlersee Cultural Landscape",
        "type": "Cultural",
        "country": "Austria, Hungary",
        "yearInscribed": "2001"
      }
    }
  ]
}