{
  "type": "FeatureCollection",
  "features": [
    {
      "type": "Feature",
      "geometry": {
        "type": "Point",
        "coordinates": [
          42.71833,
          35.58806
        ]
      },
      "properties": {
        "code": "hatra",
        "name": "Hatra",
        "type": "Cultural",
        "country": "Iraq",
        "yearInscribed": "1985"
      }
    }
  ]
}