{
  "type": "FeatureCollection",
  "features": [
    {
      "type": "Feature",
      "geometry": {
        "type": "Point",
        "coordinates": [
          16.3699,
          48.2094
        ]
      },
      "properties": {
        "code": "historic-centre-of-vienna",
        "name": "Historic Centre of Vienna",
        "type": "Cultural",
        "country": "Austria",
        "yearInscribed": "2001"
      }
    }
  ]
}