{"type":"FeatureCollection","features":[{"type":"Feature","geometry":{"type":"Point","coordinates":[155.565,50.861]},"properties":{"code":"alaid","name":"Alaid","volcanoType":"Stratovolcano","status":"Historically Active","elevation":2339,"lastEruption":"2015","vei":3}}]}
