{"type":"FeatureCollection","features":[{"type":"Feature","geometry":{"type":"Point","coordinates":[124.792,1.358]},"properties":{"code":"lokon-empung","name":"Lokon-Empung","volcanoType":"Stratovolcano","status":"Historically Active","elevation":1580,"lastEruption":"2015","vei":2}}]}
