{"type":"FeatureCollection","features":[{"type":"Feature","geometry":{"type":"Point","coordinates":[9.17,4.203]},"properties":{"code":"mount-cameroon","name":"Mount Cameroon","volcanoType":"Stratovolcano","status":"Historically Active","elevation":4095,"lastEruption":"2012","vei":2}}]}
