{"type":"FeatureCollection","features":[{"type":"Feature","geometry":{"type":"Point","coordinates":[-68.54,-27.11]},"properties":{"code":"nevado-ojos-del-salado","name":"Ojos del Salado","volcanoType":"Stratovolcano","status":"Dormant","elevation":6893,"lastEruption":"1000","vei":0}}]}
