{"type":"FeatureCollection","features":[{"type":"Feature","geometry":{"type":"Point","coordinates":[35.902,-2.764]},"properties":{"code":"ol-doinyo-lengai","name":"Ol Doinyo Lengai","volcanoType":"Stratovolcano","status":"Erupting/Recent","elevation":2962,"lastEruption":"2019","vei":2}}]}
