{"type":"FeatureCollection","features":[{"type":"Feature","geometry":{"type":"Point","coordinates":[-71.857,-15.787]},"properties":{"code":"sabancaya","name":"Sabancaya","volcanoType":"Stratovolcano","status":"Erupting/Recent","elevation":5976,"lastEruption":"2023","vei":3}}]}
