{"type":"FeatureCollection","features":[{"type":"Feature","geometry":{"type":"Point","coordinates":[129.714,29.638]},"properties":{"code":"suwanosejima","name":"Suwanosejima","volcanoType":"Stratovolcano","status":"Erupting/Recent","elevation":796,"lastEruption":"2023","vei":2}}]}
