{"type":"FeatureCollection","features":[{"type":"Feature","geometry":{"type":"Point","coordinates":[130.2986,32.757]},"properties":{"code":"unzen","name":"Mount Unzen","volcanoType":"Complex volcano","status":"Historically Active","elevation":1500,"lastEruption":"1995","vei":4}}]}
