{"type":"FeatureCollection","features":[{"type":"Feature","geometry":{"type":"Point","coordinates":[112.922,-8.1077]},"properties":{"code":"semeru","name":"Mount Semeru","volcanoType":"Stratovolcano","status":"Erupting/Recent","elevation":3676,"lastEruption":"2023","vei":3}}]}
