{"type":"FeatureCollection","features":[{"type":"Feature","geometry":{"type":"Point","coordinates":[141.2847,24.7542]},"properties":{"code":"suribachi","name":"Ioto (Iwo Jima)","volcanoType":"Caldera","status":"Historically Active","elevation":161,"lastEruption":"2012","vei":1}}]}
