{"type":"FeatureCollection","features":[{"type":"Feature","geometry":{"type":"Point","coordinates":[160.3256,55.8317]},"properties":{"code":"tolbachik","name":"Tolbachik","volcanoType":"Shield volcano","status":"Historically Active","elevation":3682,"lastEruption":"2013","vei":4}}]}
