{
  "type": "FeatureCollection",
  "features": [
    {
      "type": "Feature",
      "geometry": {
        "type": "Point",
        "coordinates": [
          13.59333333,
          37.28972222
        ]
      },
      "properties": {
        "code": "archaeological-area-of-agrigento",
        "name": "Archaeological Area of Agrigento",
        "type": "Cultural",
        "country": "Italy",
        "yearInscribed": "1997"
      }
    }
  ]
}