{
  "type": "FeatureCollection",
  "features": [
    {
      "type": "Feature",
      "geometry": {
        "type": "Point",
        "coordinates": [
          -71.980004,
          -13.517276
        ]
      },
      "properties": {
        "code": "city-of-cuzco",
        "name": "City of Cuzco",
        "type": "Cultural",
        "country": "Peru",
        "yearInscribed": "1983"
      }
    }
  ]
}