{
  "type": "FeatureCollection",
  "features": [
    {
      "type": "Feature",
      "geometry": {
        "type": "Point",
        "coordinates": [
          64.42861,
          39.77472
        ]
      },
      "properties": {
        "code": "historic-centre-of-bukhara",
        "name": "Historic Centre of Bukhara",
        "type": "Cultural",
        "country": "Uzbekistan",
        "yearInscribed": "1993"
      }
    }
  ]
}