{
  "type": "FeatureCollection",
  "features": [
    {
      "type": "Feature",
      "geometry": {
        "type": "Point",
        "coordinates": [
          -1.51056,
          48.63556
        ]
      },
      "properties": {
        "code": "mont-saint-michel-and-its-bay",
        "name": "Mont-Saint-Michel and its Bay",
        "type": "Cultural",
        "country": "France",
        "yearInscribed": "1979"
      }
    }
  ]
}