{"type":"FeatureCollection","features":[{"type":"Feature","properties":{"code":"clt","name":"Charlotte Douglas International","featureType":"airport","iataCode":"CLT","annualPassengers":45000000,"classification":"International Hub"},"geometry":{"type":"Point","coordinates":[-80.9431,35.214]}}]}
