{"type":"FeatureCollection","features":[{"type":"Feature","properties":{"code":"den","name":"Denver International","featureType":"airport","iataCode":"DEN","annualPassengers":74000000,"classification":"Mega Hub"},"geometry":{"type":"Point","coordinates":[-104.6737,39.8561]}}]}
