{"type":"FeatureCollection","features":[{"type":"Feature","properties":{"code":"yyz","name":"Toronto Pearson International","featureType":"airport","iataCode":"YYZ","annualPassengers":37000000,"classification":"Regional Hub"},"geometry":{"type":"Point","coordinates":[-79.6248,43.6777]}}]}
