{"type":"FeatureCollection","features":[{"type":"Feature","geometry":{"type":"Point","coordinates":[-17.8903,28.7619]},"properties":{"code":"cta-north","name":"Cherenkov Telescope Array North","observatoryType":"Multi-messenger","status":"Under Construction","country":"Spain"}}]}
