{"type":"FeatureCollection","features":[{"type":"Feature","geometry":{"type":"Point","coordinates":[87.1783,43.4711]},"properties":{"code":"gao-xinjiang","name":"Nanshan Station (Xinjiang Astronomical Observatory)","observatoryType":"Optical","status":"Operational","country":"China"}}]}
