{"type":"FeatureCollection","features":[{"type":"Feature","geometry":{"type":"Point","coordinates":[-17.8771,28.7622]},"properties":{"code":"int","name":"Isaac Newton Telescope","observatoryType":"Optical","status":"Operational","country":"Spain"}}]}
