{"type":"FeatureCollection","features":[{"type":"Feature","geometry":{"type":"Point","coordinates":[-111.5967,31.9583]},"properties":{"code":"kitt-peak","name":"Kitt Peak National Observatory","observatoryType":"Optical","status":"Operational","country":"United States"}}]}
