{"type":"FeatureCollection","features":[{"type":"Feature","geometry":{"type":"Point","coordinates":[-17.8797,28.7594]},"properties":{"code":"lapalma-sst","name":"Swedish 1-m Solar Telescope","observatoryType":"Optical","status":"Operational","country":"Spain"}}]}
