{"type":"FeatureCollection","features":[{"type":"Feature","geometry":{"type":"Point","coordinates":[-70.6926,-29.0146]},"properties":{"code":"magellan","name":"Magellan Telescopes","observatoryType":"Optical","status":"Operational","country":"Chile"}}]}
