{"type":"FeatureCollection","features":[{"type":"Feature","geometry":{"type":"Point","coordinates":[149.4244,-35.3708]},"properties":{"code":"molonglo","name":"Molonglo Observatory Synthesis Telescope","observatoryType":"Radio","status":"Operational","country":"Australia"}}]}
