{"type":"FeatureCollection","features":[{"type":"Feature","geometry":{"type":"Point","coordinates":[11.6469,44.5206]},"properties":{"code":"northern-cross","name":"Northern Cross Radio Telescope","observatoryType":"Radio","status":"Operational","country":"Italy"}}]}
