{"type":"FeatureCollection","features":[{"type":"Feature","geometry":{"type":"Point","coordinates":[30.3264,59.7717]},"properties":{"code":"pulkovo","name":"Pulkovo Observatory","observatoryType":"Optical","status":"Operational","country":"Russia"}}]}
