{"type":"FeatureCollection","features":[{"type":"Feature","geometry":{"type":"Point","coordinates":[9.2453,39.4931]},"properties":{"code":"sardinia","name":"Sardinia Radio Telescope","observatoryType":"Radio","status":"Operational","country":"Italy"}}]}
