{"type":"FeatureCollection","features":[{"type":"Feature","geometry":{"type":"Point","coordinates":[-155.4781,19.8242]},"properties":{"code":"sma","name":"Submillimeter Array","observatoryType":"Radio","status":"Operational","country":"United States"}}]}
