{"type":"FeatureCollection","features":[{"type":"Feature","geometry":{"type":"Point","coordinates":[-17.8827,28.7606]},"properties":{"code":"wht","name":"William Herschel Telescope","observatoryType":"Optical","status":"Operational","country":"Spain"}}]}
