{"type":"FeatureCollection","features":[{"type":"Feature","geometry":{"type":"Point","coordinates":[100.31,40.92]},"properties":{"code":"jiuquan-commercial","name":"Jiuquan Commercial Launch Zone","status":"Active","country":"China","operator":"CASC / Commercial operators"}}]}
