{"type":"FeatureCollection","features":[{"type":"Feature","geometry":{"type":"Point","coordinates":[167.7432,9.0477]},"properties":{"code":"kwajalein","name":"Omelek Island (SpaceX)","status":"Historical","country":"Marshall Islands","operator":"SpaceX (former)"}}]}
