{"type":"FeatureCollection","features":[{"type":"Feature","geometry":{"type":"Point","coordinates":[-4.9954,50.4406]},"properties":{"code":"newquay-spaceport","name":"Spaceport Cornwall","status":"Active","country":"United Kingdom","operator":"Virgin Orbit (defunct) / Others"}}]}
