{"type":"FeatureCollection","features":[{"type":"Feature","geometry":{"type":"Point","coordinates":[80.2304,13.7199]},"properties":{"code":"satish-dhawan","name":"Satish Dhawan Space Centre (SHAR)","status":"Active","country":"India","operator":"ISRO"}}]}
