{"type":"FeatureCollection","features":[{"type":"Feature","geometry":{"type":"Point","coordinates":[129.666,40.856]},"properties":{"code":"tonghae","name":"Tonghae Satellite Launching Ground (Musudan-ri)","status":"Historical","country":"North Korea","operator":"NADA"}}]}
