{
  "type": "FeatureCollection",
  "features": [
    {
      "type": "Feature",
      "geometry": {
        "type": "Point",
        "coordinates": [
          85.324,
          27.7172
        ]
      },
      "properties": {
        "code": "holi-nepal",
        "name": "Holi (Fagu Purnima)",
        "festivalType": "Cultural",
        "dateOrSeason": "March (full moon)",
        "location": "Kathmandu, Nepal"
      }
    }
  ]
}
