{"type":"FeatureCollection","features":[{"type":"Feature","geometry":{"type":"Point","coordinates":[128.9764,36.1647]},"properties":{"code":"bohyunsan","name":"Bohyunsan Optical Astronomy Observatory","observatoryType":"Optical","status":"Operational","country":"South Korea"}}]}
