{"type":"FeatureCollection","features":[{"type":"Feature","geometry":{"type":"Point","coordinates":[133.8097,-31.8686]},"properties":{"code":"ceduna","name":"Ceduna Radio Observatory","observatoryType":"Radio","status":"Operational","country":"Australia"}}]}
