{"type":"FeatureCollection","features":[{"type":"Feature","geometry":{"type":"Point","coordinates":[-69.2956,-31.7986]},"properties":{"code":"leoncito","name":"Leoncito Astronomical Complex","observatoryType":"Optical","status":"Operational","country":"Argentina"}}]}
