{"type":"FeatureCollection","features":[{"type":"Feature","geometry":{"type":"Point","coordinates":[87.1783,43.4711]},"properties":{"code":"nan-ren","name":"Nanshan Radio Observatory","observatoryType":"Radio","status":"Operational","country":"China"}}]}
