{"type":"FeatureCollection","features":[{"type":"Feature","geometry":{"type":"Point","coordinates":[174.7683,-41.2903]},"properties":{"code":"nz-carter","name":"Carter Observatory","observatoryType":"Optical","status":"Operational","country":"New Zealand"}}]}
