{"type":"FeatureCollection","features":[{"type":"Feature","geometry":{"type":"Point","coordinates":[116.7644,-26.8247]},"properties":{"code":"ska-low","name":"SKA-Low","observatoryType":"Radio","status":"Under Construction","country":"Australia"}}]}
