{"type":"FeatureCollection","features":[{"type":"Feature","geometry":{"type":"Point","coordinates":[26.4647,58.2656]},"properties":{"code":"tartu","name":"Tartu Observatory","observatoryType":"Optical","status":"Operational","country":"Estonia"}}]}
