{"type":"FeatureCollection","features":[{"type":"Feature","geometry":{"type":"Point","coordinates":[-88.5561,42.5703]},"properties":{"code":"yerkes","name":"Yerkes Observatory","observatoryType":"Optical","status":"Operational","country":"United States"}}]}
