{
  "type": "FeatureCollection",
  "features": [
    {
      "type": "Feature",
      "geometry": {
        "type": "Point",
        "coordinates": [
          77.209,
          28.6139
        ]
      },
      "properties": {
        "code": "republic-day-india",
        "name": "Republic Day",
        "festivalType": "National",
        "dateOrSeason": "January 26",
        "location": "New Delhi, India"
      }
    }
  ]
}
