{
  "type": "FeatureCollection",
  "features": [
    {
      "type": "Feature",
      "geometry": {
        "type": "Point",
        "coordinates": [
          35.2137,
          31.7683
        ]
      },
      "properties": {
        "code": "sukkot",
        "name": "Sukkot",
        "festivalType": "Seasonal",
        "dateOrSeason": "September–October (Tishrei 15)",
        "location": "Jerusalem, Israel"
      }
    }
  ]
}
